{
  "uuid": "5a4e03bb-7cdb-44f1-985f-30a5e83fa464",
  "latency": 0,
  "statusCode": 404,
  "label": "Returned if:\n\n *  the attachment is not found.\n *  attachments are disabled in the Jira settings.",
  "headers": [
    {
      "key": "Content-Type",
      "value": "application/json"
    }
  ],
  "bodyType": "INLINE",
  "filePath": "",
  "databucketID": "",
  "sendFileAsBody": false,
  "rules": [],
  "rulesOperator": "OR",
  "disableTemplating": false,
  "fallbackTo404": false,
  "default": false
}