{
  "uuid": "3a696e89-6f4e-4d44-8607-189d4c227898",
  "latency": 0,
  "statusCode": 404,
  "label": "Returned if the issue or comment is not found or the user does not have permission to view the issue or comment.",
  "headers": [
    {
      "key": "Content-Type",
      "value": "application/json"
    }
  ],
  "bodyType": "INLINE",
  "filePath": "",
  "databucketID": "",
  "sendFileAsBody": false,
  "rules": [],
  "rulesOperator": "OR",
  "disableTemplating": false,
  "fallbackTo404": false,
  "default": false
}