{
  "uuid": "30d3bb73-3352-4364-ae76-ac19cb0ce3b8",
  "latency": 0,
  "statusCode": 403,
  "label": "Returned if:\n\n *  the user does not have the necessary permission to edit the project's configuration.\n *  the Jira instance is Jira Core Free or Jira Software Free. Permission schemes cannot be assigned to projects on free plans.",
  "headers": [
    {
      "key": "Content-Type",
      "value": "application/json"
    }
  ],
  "bodyType": "INLINE",
  "filePath": "",
  "databucketID": "",
  "sendFileAsBody": false,
  "rules": [],
  "rulesOperator": "OR",
  "disableTemplating": false,
  "fallbackTo404": false,
  "default": false
}