{
  "uuid": "d9b622b2-4711-42cb-9bc3-ff1290b483fe",
  "latency": 0,
  "statusCode": 400,
  "label": "Returned if:\n* any of the provided modules is invalid. For example, required properties are missing.\n* any of the modules conflict with registered dynamic modules or modules defined in the app descriptor. For example, there are duplicate keys.\n\nDetails of the issues encountered are included in the error message.",
  "headers": [
    {
      "key": "Content-Type",
      "value": "application/json"
    }
  ],
  "bodyType": "INLINE",
  "filePath": "",
  "databucketID": "",
  "sendFileAsBody": false,
  "rules": [],
  "rulesOperator": "OR",
  "disableTemplating": false,
  "fallbackTo404": false,
  "default": false
}